closing_flow-0.1.0.dist-info/top_level.txt
closing_flow-0.1.0.dist-info/WHEEL
closing_flow-0.1.0.dist-info/METADATA
closing_flow-0.1.0.dist-info/LICENSE
closing_flow-0.1.0.dist-info/RECORD
closing_flow/__init__.py
closing_flow/closing_flow.py
closing_flow/funcs.pypy38-pp73-x86-linux-gnu.so
