Metadata-Version: 2.1
Name: closing-flow
Version: 0.1.0
Summary: Closing Flow
Home-page: https://github.com/kentechx/closing_flow
Author: Kaidi Shen
License: MIT
Requires-Python: >=3.8
License-File: LICENSE
Requires-Dist: numpy
Requires-Dist: libigl
Requires-Dist: gpytoolbox
